odoo9_addon_product_variant_supplierinfo-9.0.1.0.0-py2.7-nspkg.pth
odoo_addons/product_variant_supplierinfo/__openerp__.py
odoo_addons/product_variant_supplierinfo/__init__.py
odoo_addons/product_variant_supplierinfo/README.rst
odoo_addons/product_variant_supplierinfo/models/product_product.py
odoo_addons/product_variant_supplierinfo/models/__init__.py
odoo_addons/product_variant_supplierinfo/models/procurement.py
odoo_addons/product_variant_supplierinfo/models/product_supplierinfo.py
odoo_addons/product_variant_supplierinfo/i18n/it.po
odoo_addons/product_variant_supplierinfo/i18n/es.po
odoo_addons/product_variant_supplierinfo/i18n/sl.po
odoo_addons/product_variant_supplierinfo/i18n/fr.po
odoo_addons/product_variant_supplierinfo/i18n/pt_BR.po
odoo_addons/product_variant_supplierinfo/views/product_product_view.xml
odoo_addons/product_variant_supplierinfo/views/product_supplierinfo_view.xml
odoo_addons/product_variant_supplierinfo/tests/test_procurement.py
odoo_addons/product_variant_supplierinfo/tests/test_product_supplierinfo.py
odoo_addons/product_variant_supplierinfo/tests/__init__.py
odoo_addons/product_variant_supplierinfo/demo/procurement_demo.xml
odoo_addons/product_variant_supplierinfo/demo/product_demo.xml
odoo_addons/product_variant_supplierinfo/static/description/icon.png
odoo9_addon_product_variant_supplierinfo-9.0.1.0.0.dist-info/top_level.txt
odoo9_addon_product_variant_supplierinfo-9.0.1.0.0.dist-info/WHEEL
odoo9_addon_product_variant_supplierinfo-9.0.1.0.0.dist-info/RECORD
odoo9_addon_product_variant_supplierinfo-9.0.1.0.0.dist-info/metadata.json
odoo9_addon_product_variant_supplierinfo-9.0.1.0.0.dist-info/DESCRIPTION.rst
odoo9_addon_product_variant_supplierinfo-9.0.1.0.0.dist-info/METADATA
odoo9_addon_product_variant_supplierinfo-9.0.1.0.0.dist-info/namespace_packages.txt
